LICENSE
MANIFEST.in
README.md
requirements.txt
setup.cfg
setup.py
django_broadcast/__init__.py
django_broadcast/api.py
django_broadcast/models.py
django_broadcast/serializers.py
django_broadcast/settings.py
django_broadcast.egg-info/PKG-INFO
django_broadcast.egg-info/SOURCES.txt
django_broadcast.egg-info/dependency_links.txt
django_broadcast.egg-info/pbr.json
django_broadcast.egg-info/requires.txt
django_broadcast.egg-info/top_level.txt
django_broadcast/.idea/.name
django_broadcast/.idea/django_broadcast.iml
django_broadcast/.idea/misc.xml
django_broadcast/.idea/modules.xml
django_broadcast/.idea/vcs.xml
django_broadcast/.idea/workspace.xml
django_broadcast/django_rest_framework/__init__.py