Metadata-Version: 1.1
Name: django-broadcast
Version: 0.1.1
Summary: Video broadcasting support for Django apps
Home-page: https://github.com/PerchLive/django-broadcast
Author: David Brodsky, Chris Ballinger
Author-email: dbro@dbro.pro, chrisballinger@gmail.com
License: Apache License 2.0
Platform: UNKNOWN
Classifier: Development Status :: 2 - Pre-Alpha
Classifier: Environment :: Web Environment
Classifier: Framework :: Django
Classifier: Intended Audience :: Developers
Classifier: License :: OSI Approved :: Apache Software License
Classifier: Operating System :: OS Independent
Classifier: Natural Language :: English
Classifier: Programming Language :: Python :: 3.5
Classifier: Topic :: Internet :: WWW/HTTP
